{
    "2019": {
        "5": {
            "3": [
                {
                    "File": "DSC01318.JPG",
                    "Make": "SONY",
                    "Model": "DSC-RX100",
                    "FocalLength": 10.4,
                    "FNumber": "f/5.6",
                    "ExposureTime": "1/400",
                    "ISO": 125,
                    "time": "2019:05:03 12:22:20",
                    "timestamp": 1556857340000
                }
            ],
            "14": [
                {
                    "File": "DSC_0913.JPG",
                    "Make": "Sony",
                    "Model": "G8441",
                    "FocalLength": 4.4,
                    "FNumber": "f/2",
                    "ExposureTime": "1/50",
                    "ISO": 125,
                    "time": "2019:05:14 11:45:08",
                    "timestamp": 1557805508000
                }
            ]
        }
    }
}